indico_livesync_invenio/__init__.py
indico_livesync_invenio/backend.py
indico_livesync_invenio/connector.py
indico_livesync_invenio/plugin.py
indico_livesync_invenio/translations/messages.pot
indico_livesync_invenio/translations/fr_FR/LC_MESSAGES/messages-js.po
indico_livesync_invenio/translations/fr_FR/LC_MESSAGES/messages.mo
indico_livesync_invenio/translations/fr_FR/LC_MESSAGES/messages.po
indico_plugin_livesync_invenio-1.0rc1.dist-info/DESCRIPTION.rst
indico_plugin_livesync_invenio-1.0rc1.dist-info/METADATA
indico_plugin_livesync_invenio-1.0rc1.dist-info/RECORD
indico_plugin_livesync_invenio-1.0rc1.dist-info/WHEEL
indico_plugin_livesync_invenio-1.0rc1.dist-info/entry_points.txt
indico_plugin_livesync_invenio-1.0rc1.dist-info/metadata.json
indico_plugin_livesync_invenio-1.0rc1.dist-info/top_level.txt
