Metadata-Version: 2.0
Name: indico-plugin-livesync-invenio
Version: 1.0rc1
Summary: Invenio target for the Indico LiveSync plugin
Home-page: https://github.com/indico/indico-plugins
Author: Indico Team
Author-email: indico-team@cern.ch
License: https://www.gnu.org/licenses/gpl-3.0.txt
Platform: UNKNOWN
Classifier: Environment :: Plugins
Classifier: Environment :: Web Environment
Classifier: License :: OSI Approved :: GNU General Public License v3 or later (GPLv3+)
Classifier: Programming Language :: Python :: 2.7
Requires-Dist: indico (>=2.0a1)
Requires-Dist: indico-plugin-livesync (>=1.0.dev0)
